[{
  "_id": {
    "$oid": "666dd9cc1abfd50c030ab864"
  },
  "uid": 1,
  "peso": {
    "1": 5,
    "2": 1,
    "7": 5
  },
  "grasa": {
    "1": 5,
    "2": 1,
    "7": 5
  },
  "cintura": {
    "1": 5,
    "2": 1,
    "7": 5
  },
  "b1": {
    "1": 5,
    "2": 1,
    "7": 5
  }
},
{
  "_id": {
    "$oid": "666dd9f61abfd50c030ab865"
  },
  "uid": 2,
  "peso": {
    "1": 5,
    "3": 3,
    "4": 3
  },
  "grasa": {
    "1": 5,
    "2": 1,
    "7": 5
  },
  "cintura": {
    "1": 5,
    "2": 1,
    "7": 5
  },
  "b1": {
    "1": 5,
    "2": 1,
    "7": 5
  }
}]